syft_event/__init__.py
syft_event/cleanup.py
syft_event/deps.py
syft_event/handlers.py
syft_event/py.typed
syft_event/router.py
syft_event/schema.py
syft_event/server2.py
syft_event/types.py
syft_event-0.4.3.dist-info/METADATA
syft_event-0.4.3.dist-info/WHEEL
syft_event-0.4.3.dist-info/RECORD
