Metadata-Version: 2.4
Name: syft-event
Version: 0.4.3
Summary: A distributed event-driven RPC framework for SyftBox that enables file-based communication, request handling, and real-time file system monitoring across datasites.
Requires-Python: >=3.9
Requires-Dist: loguru>=0.7.3
Requires-Dist: pathspec>=0.12.1
Requires-Dist: pydantic>=2.10.4
Requires-Dist: syft-rpc>=0.4.1
Requires-Dist: watchdog>=6.0.0
